dissimilar-0.1.1.dist-info/METADATA
dissimilar-0.1.1.dist-info/WHEEL
dissimilar-0.1.1.dist-info/license_files/LICENSE
dissimilar/__init__.py
dissimilar/__init__.pyi
dissimilar/py.typed
dissimilar/dissimilar.cp310-win_amd64.pyd
dissimilar-0.1.1.dist-info/RECORD
