Metadata-Version: 2.1
Name: dissimilar
Version: 0.1.1
Classifier: Programming Language :: Rust
Classifier: Programming Language :: Python :: Implementation :: CPython
Classifier: Programming Language :: Python :: Implementation :: PyPy
License-File: LICENSE
Summary: A diff library with semantic cleanup
License: MIT
Requires-Python: >=3.7
Project-URL: Source Code, https://github.com/messense/py-dissimilar
